{
   "title": "मार्गणा में उदय",
   "queBlocks": [
      {
         "qType": "TRUE_FALSE",
         "que": [
            {
               "des": "सातों ही नरक में सम्यक्त्व प्रकृति का उदय हो सकता है",
               "ans": "1"
            },
            {
               "des": "नरक में साता वेदनीय का उदय हो सकता है",
               "ans": "1"
            },
            {
               "des": "पंचम गुणस्थानवर्ती तिर्यञ्च के उच्च गोत्र का उदय होता है",
               "ans": "0"
            },
            {
               "des": "आतप-उद्योत का उदय पंचेंद्रिय को होता है",
               "ans": "0"
            },
            {
               "des": "योनिमती तिर्यञ्च को स्त्री वेद का ही उदय होता है",
               "ans": "1"
            },
            {
               "des": "क्षायिक सम्यक्त्व चारों ही गति में पाया जाता है",
               "ans": "1"
            },
            {
               "des": "भोग-भूमिज तिर्यञ्च के उच्च गोत्र का उदय होता है",
               "ans": "0"
            },
            {
               "des": "तिर्यंचिनी के वज्रवृषभनाराच संहनन का उदय हो सकता है",
               "ans": "1"
            },
            {
               "des": "मनुष्यिनी के वज्रवृषभनाराच संहनन का उदय हो सकता है",
               "ans": "1"
            },
            {
               "des": "भोग-भूमि में उच्च-गोत्र का ही उदय हो सकता है",
               "ans": "0"
            },
            {
               "des": "अग्नि-कायिक जीव के आतप का उदय होता है",
               "ans": "0"
            },
            {
               "des": "मन-योग पंचेंद्रिय को ही होता है",
               "ans": "1"
            },
            {
               "des": "अवधिज्ञान के साथ उद्योत का उदय हो सकता है",
               "ans": "1"
            },
            {
               "des": "अपर्याप्त अवस्था में अवधिज्ञान का उदय नहीं होता",
               "ans": "0"
            },
            {
               "des": "मन:पर्यय ज्ञान पुरुष वेद में ही संभव है",
               "ans": "1"
            },
            {
               "des": "क्षायिक सम्यक्त्वी जीव के अपर्याप्त कर्म का उदय संभव है",
               "ans": "0"
            },
            {
               "des": "उपशम श्रेणी में तिर्यञ्च-गति का सत्त्व संभव है",
               "ans": "1"
            },
            {
               "des": "क्षायिक सम्यक्त्वी तिर्यञ्च अविरत ही होते हैं",
               "ans": "1"
            }
         ]
      },
      {
         "qType": "MTPL_CH",
         "que": [
            {
               "des": "नरक में ____ संस्थान और _____ संहनन का उदय होता है",
               "ans": "6",
               "choices": [
                  "6, सृपाटिका",
                  "हुंडक, सृपाटिका",
                  "हुंडक, 6",
                  "6,0",
                  "0,6",
                  "हुंडक, 0",
                  "0,0",
                  "इनमें से सभी",
                  "इनमें से कोई नहीं"
               ]
            },
            {
               "des": "मिथ्यादृष्टि मनुष्य के जन्म के समय लेश्या",
               "ans": "1",
               "choices": [
                  "3 अशुभ",
                  "कापोत और 3 शुभ",
                  "3 शुभ",
                  "छहों",
                  "इनमें से कोई नहीं"
               ]
            },
            {
               "des": "सम्यक्त्वी मनुष्य के जन्म के समय लेश्या",
               "ans": "4",
               "choices": [
                  "3 अशुभ",
                  "कापोत और 3 शुभ",
                  "3 शुभ",
                  "छहों",
                  "इनमें से कोई नहीं"
               ]
            },
            {
               "des": "नरक में इन प्रकृतियों का उदय होता है",
               "ans": "1",
               "choices": [
                  "शुभ-अशुभ, साता-असाता वेदनीय",
                  "अशुभ, असाता-वेदनीय",
                  "शुभ-अशुभ, असाता वेदनीय",
                  "अशुभ, साता-असाता वेदनीय",
                  "इनमें से कोई नहीं"
               ]
            },
            {
               "des": "नरक में इन प्रकृतियों का उदय होता है",
               "ans": "2",
               "choices": [
                  "स्थिर-अस्थिर, प्रशस्त-अप्रशस्त विहायोगति",
                  "स्थिर-अस्थिर, अप्रशस्त विहायोगति",
                  "अस्थिर, प्रशस्त-अप्रशस्त विहायोगति",
                  "अस्थिर, अप्रशस्त विहायोगति",
                  "इनमें से कोई नहीं"
               ]
            },
            {
               "des": "नरक में इन निद्रा का उदय होता है",
               "ans": "2",
               "choices": [
                  "पांचों निद्रा",
                  "निद्रा, प्रचला",
                  "स्त्यानत्रिक",
                  "कोई भी निद्रा का उदय नहीं"
               ]
            },
            {
               "des": "देवों में इन प्रकृतियों का उदय नहीं होता",
               "ans": "5",
               "choices": [
                  "दुर्भग, अयशस्कीर्ति",
                  "स्त्यान-त्रिक, नीच-गोत्र",
                  "अप्रशस्त विहायोगति, दु:स्वर",
                  "इनमें से कोई नहीं",
                  "इनमें से सभी"
               ]
            },
            {
               "des": "सुस्वर का उदय यहाँ नहीं होता",
               "ans": "7",
               "choices": [
                  "नरक",
                  "एकेन्द्रिय",
                  "लब्ध्यपर्याप्त",
                  "विकलत्रय",
                  "मुनि",
                  "इनमें से कोई नहीं",
                  "इनमें से एक से अधिक में पर सभी नहीं",
                  "इनमें से सभी"
               ]
            },
            {
               "des": "विग्रह गति में इन वचन-योग का उदय हो सकता है",
               "ans": "5",
               "choices": [
                  "सत्य",
                  "असत्य",
                  "उभय",
                  "अनुभय",
                  "इनमें से कोई नहीं",
                  "इनमें से एक से अधिक में पर सभी नहीं",
                  "इनमें से सभी"
               ]
            },
            {
               "des": "अनुभय वचन इनके नहीं होते",
               "ans": "6",
               "choices": [
                  "एकेन्द्रिय",
                  "साधारण",
                  "चतुरिंद्रिय",
                  "विग्रह-गति",
                  "इनमें से कोई नहीं",
                  "इनमें से एक से अधिक में पर सभी नहीं",
                  "इनमें से सभी"
               ]
            },
            {
               "des": "औदारिक काययोग वाले के इन प्रकृतियों का उदय नहीं है",
               "ans": "6",
               "choices": [
                  "तिर्यञ्च आनुपूर्व्य",
                  "तीर्थंकर",
                  "आहारक-अंगोपांग",
                  "वैक्रियिक शरीर",
                  "इनमें से कोई नहीं",
                  "इनमें से एक से अधिक में पर सभी नहीं",
                  "इनमें से सभी"
               ]
            },
            {
               "des": "परिहारविशुद्धि संयमी के इन प्रकृतियों का उदय हो सकता है",
               "ans": "4",
               "choices": [
                  "स्त्री-वेद",
                  "तीर्थंकर",
                  "आहारक-द्विक",
                  "स्त्यान-त्रिक",
                  "इनमें से कोई नहीं",
                  "इनमें से एक से अधिक में पर सभी नहीं",
                  "इनमें से सभी"
               ]
            },
            {
               "des": "इस वेद में ही तीर्थंकर प्रकृति का उदय संभव है",
               "ans": "4",
               "choices": [
                  "पुरुष",
                  "स्त्री",
                  "नपुंसक",
                  "इनमें से कोई नहीं",
                  "इनमें से सभी"
               ]
            },
            {
               "des": "तीर्थंकर प्रकृति के उदय के समय इतनी लेश्याओं का उदय होता है",
               "ans": "4",
               "choices": [
                  "छहों",
                  "तीन शुभ",
                  "शुक्ल-लेश्या",
                  "शुक्ल या अलेश्य",
                  "अलेश्य",
                  "इनमें से कोई नहीं"
               ]
            },
            {
               "des": "तिर्यञ्च के जन्म के समय संभव लेश्या",
               "ans": "3",
               "choices": [
                  "छहों",
                  "तीन शुभ",
                  "तीन अशुभ",
                  "कापोत",
                  "अलेश्य",
                  "इनमें से कोई नहीं"
               ]
            },
            {
               "des": "सयोग-केवली गुणस्थान में सत्ता से व्युछिन्न होने वाली प्रकृतियों की संख्या ____ है",
               "ans": "1",
               "choices": [
                  "0",
                  "72",
                  "13",
                  "85",
                  "63",
                  "इनमें से कोई नहीं"
               ]
            },
            {
               "des": "अनाहारक जीव के इन कर्मों को उदय हो सकता है",
               "ans": "6",
               "choices": [
                  "स्त्री-वेद",
                  "नीच गोत्र",
                  "तीर्थंकर",
                  "प्रत्येक",
                  "इनमें से सभी",
                  "इनमें से एक से अधिक में पर सभी नहीं",
                  "इनमें से कोई नहीं"
               ]
            },
            {
               "des": "सासादन गुणस्थान में इन प्रकृतियों का उदय नहीं होता",
               "ans": "5",
               "choices": [
                  "आतप",
                  "अपर्याप्त",
                  "नरकानुपूर्व्य",
                  "साधारण",
                  "इनमें से सभी",
                  "इनमें से कोई नहीं"
               ]
            },
            {
               "des": "वैक्रियिक-मिश्र अवस्था में इन प्रकृतियों का उदय हो सकता है",
               "ans": "6",
               "choices": [
                  "उच्छ्वास",
                  "स्वर-द्विक",
                  "विहायोगति-द्विक",
                  "देव-आनुपूर्व्य",
                  "इनमें से सभी",
                  "इनमें से कोई नहीं"
               ]
            },
            {
               "des": "मनुष्य-पर्याप्त मार्गणा में इस वेद का उदय है",
               "ans": "4",
               "choices": [
                  "पुरुष",
                  "स्त्री",
                  "नपुंसक",
                  "पुरुष / नपुंसक",
                  "स्त्री / नपुंसक",
                  "स्त्री / पुरुष / नपुंसक"
               ]
            },
            {
               "des": "स्त्री वेद मार्गणा में सासादन गुणस्थान में 4 आनुपूर्वी में से ____ की उदय वुच्छिति है",
               "ans": "4",
               "choices": [
                  "0",
                  "1",
                  "2",
                  "3",
                  "4"
               ]
            },
            {
               "des": "नपुंसक वेद मार्गणा में सासादन गुणस्थान में 4 आनुपूर्वी में से ____ की उदय वुच्छिति है",
               "ans": "3",
               "choices": [
                  "0",
                  "1",
                  "2",
                  "3",
                  "4"
               ]
            },
            {
               "des": "अपर्याप्त प्रकृति का उदय _________ में ही संभव है",
               "ans": "6",
               "choices": [
                  "नरक",
                  "तिर्यञ्च",
                  "मनुष्य",
                  "देव",
                  "नरक / तिर्यञ्च",
                  "तिर्यञ्च / मनुष्य",
                  "इनमें से सभी",
                  "इनमें से कोई नहीं"
               ]
            }
         ]
      },
      {
         "qType": "TABLE_GRID_CHOSE",
         "que": {
            "des": "नीचे दिये गए कर्मों का उदय किस गुणस्थान तक पाया जाता है -",
            "qColumn": [
               {
                  "c": "सृपाटिका संहनन",
                  "ans": "7"
               },
               {
                  "c": "नाराच",
                  "ans": "11"
               },
               {
                  "c": "वज्रवृषभनाराच संहनन",
                  "ans": "13"
               },
               {
                  "c": "हुंडक संस्थान",
                  "ans": "13"
               },
               {
                  "c": "समचतुरस्र-संस्थान",
                  "ans": "13"
               },
               {
                  "c": "नपुंसक-वेद",
                  "ans": "9"
               },
               {
                  "c": "अप्रशस्त विहायोगति",
                  "ans": "13"
               },
               {
                  "c": "स्थावर",
                  "ans": "2"
               },
               {
                  "c": "अशुभ",
                  "ans": "13"
               },
               {
                  "c": "मान",
                  "ans": "9"
               },
               {
                  "c": "प्रचला",
                  "ans": "12"
               },
               {
                  "c": "उच्च-गोत्र",
                  "ans": "14"
               },
               {
                  "c": "दुर्भग",
                  "ans": "4"
               },
               {
                  "c": "सुभग",
                  "ans": "14"
               },
               {
                  "c": "दु:स्वर",
                  "ans": "13"
               },
               {
                  "c": "स्त्यानगृद्धि",
                  "ans": "6"
               },
               {
                  "c": "पद्म-लेश्या",
                  "ans": "7"
               },
               {
                  "c": "अनाहारक में पुरुष वेद की व्युच्छिति",
                  "ans": "4"
               }
            ],
            "aRow": {
               "c": "उदय"
            },
            "aColumn": [
               "1 मिथ्यात्व गुणस्थान",
               "2 सासादन गुणस्थान",
               "3 मिश्र गुणस्थान",
               "4 अविरत सम्यक्त्व गुणस्थान",
               "5 देशविरत गुणस्थान",
               "6 प्रमत्तविरत गुणस्थान",
               "7 अप्रमत्तविरत गुणस्थान",
               "8 अपूर्वकरण गुणस्थान",
               "9 अनिवृत्तिकरण गुणस्थान",
               "10 सूक्ष्म साम्पराय गुणस्थान",
               "11 उपशान्त मोह गुणस्थान",
               "12 क्षीणमोह गुणस्थान",
               "13 सयोगकेवली गुणस्थान",
               "14 अयोगकेवली गुणस्थान",
               "-NA-"
            ]
         }
      },
      {
         "qType": "TABLE_GRID_CHOSE",
         "que": {
            "des": "नीचे दिये गए कर्मों की सत्ता किस गुणस्थान तक पायी जाती है -",
            "qColumn": [
               {
                  "c": "मिथ्यात्व",
                  "ans": "11"
               },
               {
                  "c": "सम्यक्त्व-प्रकृति",
                  "ans": "11"
               },
               {
                  "c": "मति-ज्ञानावरणी",
                  "ans": "12"
               },
               {
                  "c": "निद्रा",
                  "ans": "12"
               },
               {
                  "c": "नीच-गोत्र",
                  "ans": "14"
               },
               {
                  "c": "देव-गति",
                  "ans": "14"
               },
               {
                  "c": "नरकायु",
                  "ans": "4"
               },
               {
                  "c": "तिर्यञ्चायु",
                  "ans": "5"
               },
               {
                  "c": "प्रत्याख्यान क्रोध की सत्ता व्युच्छित्ति क्षपक-श्रेणी के इस गुणस्थान में होती है",
                  "ans": "9"
               },
               {
                  "c": "नपुंसक-वेद की सत्ता व्युच्छित्ति क्षपक-श्रेणी के इस गुणस्थान में होती है",
                  "ans": "9"
               }
            ],
            "aRow": {
               "c": "सत्त्व"
            },
            "aColumn": [
               "1 मिथ्यात्व गुणस्थान",
               "2 सासादन गुणस्थान",
               "3 मिश्र गुणस्थान",
               "4 अविरत सम्यक्त्व गुणस्थान",
               "5 देशविरत गुणस्थान",
               "6 प्रमत्तविरत गुणस्थान",
               "7 अप्रमत्तविरत गुणस्थान",
               "8 अपूर्वकरण गुणस्थान",
               "9 अनिवृत्तिकरण गुणस्थान",
               "10 सूक्ष्म साम्पराय गुणस्थान",
               "11 उपशान्त मोह गुणस्थान",
               "12 क्षीणमोह गुणस्थान",
               "13 सयोगकेवली गुणस्थान",
               "14 अयोगकेवली गुणस्थान",
               "-NA-"
            ]
         }
      },
      {
         "qType": "TABLE_GRID_CHOSE",
         "que": {
            "des": "संख्या चुनिये -",
            "qColumn": [
               {
                  "c": "नरक में पाई जाने वाली लेश्या",
                  "ans": "3"
               },
               {
                  "c": "देवों में पाई जाने वाली लेश्या",
                  "ans": "6"
               },
               {
                  "c": "वैमानिक देवों में पाई जाने वाली लेश्या",
                  "ans": "3"
               },
               {
                  "c": "ग्रैवेयिक में पाई जाने वाली लेश्या",
                  "ans": "1"
               },
               {
                  "c": "चारों गतियों में से सम्यक्त्वी जीव को नीच गोत्र का उदय इतनी गतियों में हो सकता है",
                  "ans": "3"
               },
               {
                  "c": "भोग-भूमि में निद्रा (पाँच में से)",
                  "ans": "2"
               },
               {
                  "c": "भोग-भूमि में वेद",
                  "ans": "2"
               },
               {
                  "c": "एकेन्द्रिय के संहनन",
                  "ans": "14"
               },
               {
                  "c": "विकलत्रय के संस्थान",
                  "ans": "1"
               },
               {
                  "c": "विकलत्रय के संहनन",
                  "ans": "1"
               },
               {
                  "c": "असंज्ञी के संहनन",
                  "ans": "1"
               },
               {
                  "c": "असंज्ञी के संस्थान",
                  "ans": "1"
               },
               {
                  "c": "वैक्रियिक काय-योग के संस्थान",
                  "ans": "2"
               },
               {
                  "c": "वचन-योग की जाति (एकेन्द्रिय आदि पाँच में से)",
                  "ans": "4"
               },
               {
                  "c": "चक्षु-दर्शन की जाति (एकेन्द्रिय आदि पाँच में से)",
                  "ans": "2"
               },
               {
                  "c": "औदारिक-मिश्र के गुणस्थान",
                  "ans": "4"
               },
               {
                  "c": "तीर्थंकर नामकर्म के सत्त्व इतने गुणस्थान में संभव है",
                  "ans": "12"
               },
               {
                  "c": "आहारक-शरीर के सत्त्व इतने गुणस्थान में संभव है",
                  "ans": "13"
               },
               {
                  "c": "स्त्री वेद का सत्त्व इतने गुणस्थान में संभव है",
                  "ans": "11"
               },
               {
                  "c": "अप्रत्याख्यान क्रोध का सत्त्व इतने गुणस्थान में संभव है",
                  "ans": "11"
               },
               {
                  "c": "कार्मण-काययोग के गुणस्थान",
                  "ans": "4"
               },
               {
                  "c": "निवृत्त्यपर्याप्त के गुणस्थान",
                  "ans": "5"
               },
               {
                  "c": "मनुष्यिनी के गुणस्थान",
                  "ans": "14"
               },
               {
                  "c": "दो-इंद्रिय के गुणस्थान",
                  "ans": "2"
               },
               {
                  "c": "तिर्यञ्च निवृत्त्यपर्याप्त के गुणस्थान",
                  "ans": "3"
               },
               {
                  "c": "नारकी निवृत्त्यपर्याप्त के गुणस्थान",
                  "ans": "2"
               },
               {
                  "c": "त्रस के गुणस्थान",
                  "ans": "14"
               },
               {
                  "c": "सत्य वचन-योग के गुणस्थान",
                  "ans": "13"
               },
               {
                  "c": "असत्य वचन-योग के गुणस्थान",
                  "ans": "12"
               },
               {
                  "c": "स्त्री-वेद मार्गणा में गुणस्थान",
                  "ans": "9"
               },
               {
                  "c": "पुरुष-वेद मार्गणा में गुणस्थान",
                  "ans": "9"
               },
               {
                  "c": "नपुंसक-वेद मार्गणा में गुणस्थान",
                  "ans": "9"
               },
               {
                  "c": "कृष्ण-लेश्या के गुणस्थान",
                  "ans": "4"
               },
               {
                  "c": "पद्म-लेश्या के गुणस्थान",
                  "ans": "7"
               },
               {
                  "c": "शुक्ल-लेश्या के गुणस्थान",
                  "ans": "13"
               },
               {
                  "c": "कुश्रुत ज्ञान के गुणस्थान",
                  "ans": "2"
               },
               {
                  "c": "अवधिज्ञानी  के गुणस्थान",
                  "ans": "9"
               },
               {
                  "c": "मन:पर्ययज्ञानी के गुणस्थान",
                  "ans": "7"
               },
               {
                  "c": "मानी के गुणस्थान",
                  "ans": "9"
               },
               {
                  "c": "लोभी के गुणस्थान",
                  "ans": "10"
               },
               {
                  "c": "सामायिक-संयम के गुणस्थान",
                  "ans": "4"
               },
               {
                  "c": "छेदोपस्थापना-संयमी के गुणस्थान",
                  "ans": "4"
               },
               {
                  "c": "परिहार-विशुद्धि-संयमी के गुणस्थान",
                  "ans": "2"
               },
               {
                  "c": "यथाख्यात-संयमी के गुणस्थान",
                  "ans": "4"
               },
               {
                  "c": "संज्ञी के गुणस्थान",
                  "ans": "12"
               },
               {
                  "c": "अनाहारक के गुणस्थान",
                  "ans": "5"
               },
               {
                  "c": "उपशम सम्यक्त्व के गुणस्थान",
                  "ans": "8"
               },
               {
                  "c": "क्षायोपशमिक सम्यक्त्व के गुणस्थान",
                  "ans": "4"
               },
               {
                  "c": "क्षयिक सम्यक्त्व के गुणस्थान",
                  "ans": "11"
               },
               {
                  "c": "सम्यक्त्व मार्गणा के भेद",
                  "ans": "6"
               },
               {
                  "c": "अभव्य के गुणस्थान",
                  "ans": "1"
               },
               {
                  "c": "आहार मार्गणा में आहारक के गुणस्थान",
                  "ans": "13"
               }
            ],
            "aRow": {
               "c": "संख्या"
            },
            "aColumn": [
               "1",
               "2",
               "3",
               "4",
               "5",
               "6",
               "7",
               "8",
               "9",
               "10",
               "11",
               "12",
               "13",
               "14",
               "इनमें से कोई नहीं"
            ]
         }
      }
   ]
}